PyOcclusion/__init__.py
PyOcclusion/noise.py
PyOcclusion/occlusion.py
PyOcclusion/shapes.py
PyOcclusion-1.0.2.dist-info/LICENSE
PyOcclusion-1.0.2.dist-info/METADATA
PyOcclusion-1.0.2.dist-info/WHEEL
PyOcclusion-1.0.2.dist-info/top_level.txt
PyOcclusion-1.0.2.dist-info/RECORD
