Metadata-Version: 2.1
Name: PyOcclusion
Version: 1.0.2
Summary: A package for video editing with occlusion noise
Home-page: https://github.com/BohdanSynytskyi/PyOcclusion
Author: Bohdan Synytskyi
Author-email: bodiasynytskiy@gmail.com
License: UNKNOWN
Platform: UNKNOWN
Classifier: Programming Language :: Python :: 3
Classifier: License :: OSI Approved :: MIT License
Classifier: Operating System :: OS Independent
Requires-Python: >=3.6
Requires-Dist: numpy
Requires-Dist: scikit-image
Requires-Dist: imageio
Requires-Dist: av
Requires-Dist: Pillow (>=10.0.1)
Requires-Dist: matplotlib
